WinSocketTB/SocketTB.py
WinSocketTB/__init__.py
WinSocketTB/test.py
WinSocketTB/IDownload/background.js
WinSocketTB/IDownload/center.html
WinSocketTB/IDownload/center.js
WinSocketTB/IDownload/desktop.ini
WinSocketTB/IDownload/downloader.py
WinSocketTB/IDownload/icon_48.png
WinSocketTB/IDownload/idownload.bat
WinSocketTB/IDownload/idownload.py
WinSocketTB/IDownload/idownload_E.json
WinSocketTB/IDownload/idownload_F.json
WinSocketTB/IDownload/manifest.json
WinSocketTB/IDownload/options.html
WinSocketTB/IDownload/options.js
WinSocketTB/IDownload/websocket.py
winsockettb-1.4.1.dist-info/licenses/LICENSE
winsockettb-1.4.1.dist-info/METADATA
winsockettb-1.4.1.dist-info/WHEEL
winsockettb-1.4.1.dist-info/top_level.txt
winsockettb-1.4.1.dist-info/RECORD
