Metadata-Version: 2.4
Name: WinSocketTB
Version: 1.4.1
Summary: A module in Python 3 consisting of a toolbox to handle sockets under Windows for various purposes
Home-page: https://github.com/PCigales/WinSocketTB
Author: PCigales
License: GPL-3.0-or-later
Project-URL: Bug Tracker, https://github.com/PCigales/WinSocketTB/issues
Keywords: socket,winsock2,tls-in-tls,tcp,udp,http,websocket,ntp,totp,downloader
Platform: win64
Classifier: Programming Language :: Python :: 3
Classifier: Operating System :: Microsoft :: Windows
Classifier: Development Status :: 5 - Production/Stable
Classifier: Topic :: Software Development :: Libraries :: Python Modules
Classifier: Topic :: System :: Networking
Requires-Python: >=3.8
License-File: LICENSE
Dynamic: license-file
